atwavpy/__init__.py
atwavpy/field.py
atwavpy/optics.py
atwavpy/plotting.py
atwavpy/prop.py
atwavpy/utilities.py
atwavpy-0.0.1.dist-info/LICENSE.txt
atwavpy-0.0.1.dist-info/METADATA
atwavpy-0.0.1.dist-info/WHEEL
atwavpy-0.0.1.dist-info/top_level.txt
atwavpy-0.0.1.dist-info/RECORD
