Metadata-Version: 2.1
Name: atwavpy
Version: 0.0.1
Summary: Simualtion of optical elements.
Home-page: https://github.com/tejmoxham/atwavpy/
Author: Thomas E.J. Moxham
Author-email: tej.moxham@gmail.com
License: UNKNOWN
Platform: UNKNOWN
License-File: LICENSE.txt
Requires-Dist: numpy
Requires-Dist: scipy
